admin_confirm/__init__.py
admin_confirm/admin.py
admin_confirm/constants.py
admin_confirm/file_cache.py
admin_confirm/utils.py
admin_confirm/static/admin/css/confirmation.css
admin_confirm/templates/admin/action_confirmation.html
admin_confirm/templates/admin/change_confirmation.html
admin_confirm/templates/admin/change_data.html
admin_confirm/templates/admin/submit_line.html
admin_confirm/templatetags/__init__.py
admin_confirm/templatetags/formatting.py
django_admin_confirm_cn-0.2.5.dist-info/LICENSE
django_admin_confirm_cn-0.2.5.dist-info/METADATA
django_admin_confirm_cn-0.2.5.dist-info/WHEEL
django_admin_confirm_cn-0.2.5.dist-info/top_level.txt
django_admin_confirm_cn-0.2.5.dist-info/RECORD
