Metadata-Version: 2.1
Name: django-admin-confirm-cn
Version: 0.2.5
Summary: Adds confirmation to Django Admin changes, additions and actions
Home-page: https://github.com/trangpham/django-admin-confirm/
Author: Thu Trang Pham
Author-email: thuutrangpham@gmail.com
License: Apache 2.0
Project-URL: Release Notes, https://github.com/TrangPham/django-admin-confirm/releases
Platform: UNKNOWN
Classifier: Framework :: Django :: 4.0
Classifier: Programming Language :: Python :: 3.8
Classifier: Programming Language :: Python :: 3.9
Classifier: Programming Language :: Python :: 3 :: Only
Requires-Python: >=3.8
License-File: LICENSE
Requires-Dist: Django (>=4.0)
